ad9546.py
ad9546-0.0.1.data/scripts/calib.py
ad9546-0.0.1.data/scripts/distrib.py
ad9546-0.0.1.data/scripts/irq.py
ad9546-0.0.1.data/scripts/misc.py
ad9546-0.0.1.data/scripts/mx-pin.py
ad9546-0.0.1.data/scripts/pll.py
ad9546-0.0.1.data/scripts/power-down.py
ad9546-0.0.1.data/scripts/ref-input.py
ad9546-0.0.1.data/scripts/regmap-diff.py
ad9546-0.0.1.data/scripts/regmap.py
ad9546-0.0.1.data/scripts/reset.py
ad9546-0.0.1.data/scripts/status.py
ad9546-0.0.1.data/scripts/sysclk.py
ad9546-0.0.1.data/scripts/uts.py
ad9546-0.0.1.dist-info/LICENSE
ad9546-0.0.1.dist-info/METADATA
ad9546-0.0.1.dist-info/WHEEL
ad9546-0.0.1.dist-info/top_level.txt
ad9546-0.0.1.dist-info/RECORD
