Metadata-Version: 2.1
Name: ad9546
Version: 0.0.1
Summary: Analog Devices AD9545,AD9546 clock synth management tools
Home-page: https://github.com/gwbres/adi-ad9546
Author: Guillaume W. Bres
Author-email: guillaume.bressaix@gmail.com
License: GPL-v3
License-File: LICENSE
Requires-Dist: smbus
